{"spotId":"3bp-bb-vs-btn","street":"flop","board":[{"rank":"Q","suit":"spades"},{"rank":"Q","suit":"diamonds"},{"rank":"6","suit":"clubs"}],"phase":"lead","potBB":22.5,"effStackBB":89,"betFrac":0.66,"source":"solver_precomputed","exploitability":0.0004,"bettingAware":true,"iters":250,"fullEnumeration":true,"strategy":{"AhAs":[{"action":"check","frequency":0.4996,"ev":7.533},{"action":"raise","sizeBB":14.85,"frequency":0.5004,"ev":7.21}],"AdAs":[{"action":"check","frequency":0.4325,"ev":7.229},{"action":"raise","sizeBB":14.85,"frequency":0.5675,"ev":6.971}],"AcAs":[{"action":"check","frequency":0.3471,"ev":7.701},{"action":"raise","sizeBB":14.85,"frequency":0.6529,"ev":7.394}],"AdAh":[{"action":"check","frequency":0.4995,"ev":7.533},{"action":"raise","sizeBB":14.85,"frequency":0.5005,"ev":7.21}],"AcAh":[{"action":"check","frequency":0.4037,"ev":8.008},{"action":"raise","sizeBB":14.85,"frequency":0.5963,"ev":7.649}],"AcAd":[{"action":"check","frequency":0.3471,"ev":7.701},{"action":"raise","sizeBB":14.85,"frequency":0.6529,"ev":7.394}],"KhKs":[{"action":"check","frequency":0.3417,"ev":5.924},{"action":"raise","sizeBB":14.85,"frequency":0.6583,"ev":5.649}],"KdKs":[{"action":"check","frequency":0.4364,"ev":5.259},{"action":"raise","sizeBB":14.85,"frequency":0.5636,"ev":5.033}],"KcKs":[{"action":"check","frequency":0.3079,"ev":5.923},{"action":"raise","sizeBB":14.85,"frequency":0.6921,"ev":5.659}],"KdKh":[{"action":"check","frequency":0.3417,"ev":5.924},{"action":"raise","sizeBB":14.85,"frequency":0.6583,"ev":5.649}],"KcKh":[{"action":"check","frequency":0.1693,"ev":6.601},{"action":"raise","sizeBB":14.85,"frequency":0.8307,"ev":6.306}],"KcKd":[{"action":"check","frequency":0.3079,"ev":5.923},{"action":"raise","sizeBB":14.85,"frequency":0.6921,"ev":5.659}],"QcQh":[{"action":"check","frequency":0.5328,"ev":37.02},{"action":"raise","sizeBB":14.85,"frequency":0.4672,"ev":34.855}],"JhJs":[{"action":"check","frequency":0.218,"ev":0.028},{"action":"raise","sizeBB":14.85,"frequency":0.782,"ev":0.046}],"JdJs":[{"action":"check","frequency":0.5946,"ev":-0.722},{"action":"raise","sizeBB":14.85,"frequency":0.4054,"ev":-0.699}],"JcJs":[{"action":"check","frequency":0.5436,"ev":-0.113},{"action":"raise","sizeBB":14.85,"frequency":0.4564,"ev":-0.11}],"JdJh":[{"action":"check","frequency":0.2179,"ev":0.028},{"action":"raise","sizeBB":14.85,"frequency":0.7821,"ev":0.046}],"JcJh":[{"action":"check","frequency":0.0012,"ev":0.311},{"action":"raise","sizeBB":14.85,"frequency":0.9988,"ev":0.924}],"JcJd":[{"action":"check","frequency":0.5435,"ev":-0.113},{"action":"raise","sizeBB":14.85,"frequency":0.4565,"ev":-0.11}],"ThTs":[{"action":"check","frequency":0.8288,"ev":-5.973},{"action":"raise","sizeBB":14.85,"frequency":0.1712,"ev":-5.739}],"TdTs":[{"action":"check","frequency":0.4352,"ev":-5.94},{"action":"raise","sizeBB":14.85,"frequency":0.5648,"ev":-5.759}],"TcTs":[{"action":"check","frequency":0.7987,"ev":-5.788},{"action":"raise","sizeBB":14.85,"frequency":0.2013,"ev":-5.554}],"TdTh":[{"action":"check","frequency":0.8287,"ev":-5.973},{"action":"raise","sizeBB":14.85,"frequency":0.1713,"ev":-5.739}],"TcTh":[{"action":"check","frequency":0.027,"ev":-5.636},{"action":"raise","sizeBB":14.85,"frequency":0.973,"ev":-5.25}],"TcTd":[{"action":"check","frequency":0.7987,"ev":-5.788},{"action":"raise","sizeBB":14.85,"frequency":0.2013,"ev":-5.554}],"AsKs":[{"action":"check","frequency":0.2753,"ev":-9.056},{"action":"raise","sizeBB":14.85,"frequency":0.7247,"ev":-8.715}],"AhKh":[{"action":"check","frequency":0.1751,"ev":-10.089},{"action":"raise","sizeBB":14.85,"frequency":0.8249,"ev":-9.73}],"AdKd":[{"action":"check","frequency":0.2753,"ev":-9.056},{"action":"raise","sizeBB":14.85,"frequency":0.7247,"ev":-8.715}],"AcKc":[{"action":"check","frequency":0.0851,"ev":-8.612},{"action":"raise","sizeBB":14.85,"frequency":0.9149,"ev":-8.21}],"AhQh":[{"action":"check","frequency":0.0001,"ev":28.428},{"action":"raise","sizeBB":14.85,"frequency":0.9999,"ev":28.958}],"AcQc":[{"action":"check","frequency":0.0002,"ev":29.254},{"action":"raise","sizeBB":14.85,"frequency":0.9998,"ev":29.704}],"5sAs":[{"action":"check","frequency":0.1688,"ev":-8.735},{"action":"raise","sizeBB":14.85,"frequency":0.8312,"ev":-8.78}],"5hAh":[{"action":"check","frequency":0.688,"ev":-9.487},{"action":"raise","sizeBB":14.85,"frequency":0.312,"ev":-9.573}],"5dAd":[{"action":"check","frequency":0.1687,"ev":-8.735},{"action":"raise","sizeBB":14.85,"frequency":0.8313,"ev":-8.78}],"5cAc":[{"action":"check","frequency":0.003,"ev":-9.045},{"action":"raise","sizeBB":14.85,"frequency":0.997,"ev":-8.64}],"4sAs":[{"action":"check","frequency":0.1313,"ev":-8.726},{"action":"raise","sizeBB":14.85,"frequency":0.8687,"ev":-8.767}],"4hAh":[{"action":"check","frequency":0.7363,"ev":-9.479},{"action":"raise","sizeBB":14.85,"frequency":0.2637,"ev":-9.572}],"4dAd":[{"action":"check","frequency":0.1312,"ev":-8.726},{"action":"raise","sizeBB":14.85,"frequency":0.8688,"ev":-8.766}],"4cAc":[{"action":"check","frequency":0.0029,"ev":-9.039},{"action":"raise","sizeBB":14.85,"frequency":0.9971,"ev":-8.626}],"3sAs":[{"action":"check","frequency":0.1435,"ev":-8.719},{"action":"raise","sizeBB":14.85,"frequency":0.8565,"ev":-8.764}],"3hAh":[{"action":"check","frequency":0.7717,"ev":-9.47},{"action":"raise","sizeBB":14.85,"frequency":0.2283,"ev":-9.571}],"3dAd":[{"action":"check","frequency":0.1433,"ev":-8.719},{"action":"raise","sizeBB":14.85,"frequency":0.8567,"ev":-8.764}],"3cAc":[{"action":"check","frequency":0.0028,"ev":-9.038},{"action":"raise","sizeBB":14.85,"frequency":0.9972,"ev":-8.624}],"2sAs":[{"action":"check","frequency":0.1545,"ev":-8.712},{"action":"raise","sizeBB":14.85,"frequency":0.8455,"ev":-8.76}],"2hAh":[{"action":"check","frequency":0.8087,"ev":-9.461},{"action":"raise","sizeBB":14.85,"frequency":0.1913,"ev":-9.57}],"2dAd":[{"action":"check","frequency":0.1544,"ev":-8.712},{"action":"raise","sizeBB":14.85,"frequency":0.8456,"ev":-8.76}],"2cAc":[{"action":"check","frequency":0.0029,"ev":-9.035},{"action":"raise","sizeBB":14.85,"frequency":0.9971,"ev":-8.62}],"KhQh":[{"action":"check","frequency":0.0256,"ev":25.046},{"action":"raise","sizeBB":14.85,"frequency":0.9744,"ev":23.938}],"KcQc":[{"action":"check","frequency":0.0358,"ev":25.723},{"action":"raise","sizeBB":14.85,"frequency":0.9642,"ev":24.594}],"AsKh":[{"action":"check","frequency":0.4901,"ev":-9.844},{"action":"raise","sizeBB":14.85,"frequency":0.5099,"ev":-9.849}],"AsKd":[{"action":"check","frequency":0.8428,"ev":-9.755},{"action":"raise","sizeBB":14.85,"frequency":0.1572,"ev":-9.939}],"AsKc":[{"action":"check","frequency":0.4089,"ev":-9.807},{"action":"raise","sizeBB":14.85,"frequency":0.5911,"ev":-9.743}],"AhKs":[{"action":"check","frequency":0.6543,"ev":-9.827},{"action":"raise","sizeBB":14.85,"frequency":0.3457,"ev":-9.893}],"AhKd":[{"action":"check","frequency":0.6543,"ev":-9.827},{"action":"raise","sizeBB":14.85,"frequency":0.3457,"ev":-9.893}],"AhKc":[{"action":"check","frequency":0.2159,"ev":-10.002},{"action":"raise","sizeBB":14.85,"frequency":0.7841,"ev":-9.663}],"AdKs":[{"action":"check","frequency":0.8428,"ev":-9.755},{"action":"raise","sizeBB":14.85,"frequency":0.1572,"ev":-9.939}],"AdKh":[{"action":"check","frequency":0.4901,"ev":-9.844},{"action":"raise","sizeBB":14.85,"frequency":0.5099,"ev":-9.849}],"AdKc":[{"action":"check","frequency":0.409,"ev":-9.807},{"action":"raise","sizeBB":14.85,"frequency":0.591,"ev":-9.743}],"AcKs":[{"action":"check","frequency":0.4878,"ev":-9.819},{"action":"raise","sizeBB":14.85,"frequency":0.5122,"ev":-9.785}],"AcKh":[{"action":"check","frequency":0.2348,"ev":-9.948},{"action":"raise","sizeBB":14.85,"frequency":0.7652,"ev":-9.638}],"AcKd":[{"action":"check","frequency":0.4877,"ev":-9.819},{"action":"raise","sizeBB":14.85,"frequency":0.5123,"ev":-9.785}],"AsQh":[{"action":"check","frequency":0.0002,"ev":28.668},{"action":"raise","sizeBB":14.85,"frequency":0.9998,"ev":29.5}],"AsQc":[{"action":"check","frequency":0.0002,"ev":28.953},{"action":"raise","sizeBB":14.85,"frequency":0.9998,"ev":29.662}],"AhQc":[{"action":"check","frequency":0.0001,"ev":28.961},{"action":"raise","sizeBB":14.85,"frequency":0.9999,"ev":29.421}],"AdQh":[{"action":"check","frequency":0.0002,"ev":28.668},{"action":"raise","sizeBB":14.85,"frequency":0.9998,"ev":29.5}],"AdQc":[{"action":"check","frequency":0.0002,"ev":28.953},{"action":"raise","sizeBB":14.85,"frequency":0.9998,"ev":29.662}],"AcQh":[{"action":"check","frequency":0.0001,"ev":28.805},{"action":"raise","sizeBB":14.85,"frequency":0.9999,"ev":29.56}]},"meta":{"sourceName":"self CFR (flop, chance-node turn+river)","license":"self-generated","version":"1"}}